gbdtransformation/__init__.py
gbdtransformation/execs-nico.py
gbdtransformation/execs.py
gbdtransformation/gbd-transform.exec.tgz
gbdtransformation/parser.py
gbdtransformation/renders.py
gbdtransformation/brands/__init__.py
gbdtransformation/brands/filters.py
gbdtransformation/brands/aetm/__init__.py
gbdtransformation/brands/aetm/filters.py
gbdtransformation/brands/aetm/schema
gbdtransformation/brands/aetm/template.yml
gbdtransformation/brands/aetm/tests/__init__.py
gbdtransformation/brands/altm/__init__.py
gbdtransformation/brands/altm/filters.py
gbdtransformation/brands/altm/schema
gbdtransformation/brands/altm/template.yml
gbdtransformation/brands/altm/tests/__init__.py
gbdtransformation/brands/altm/tests/altm.xml
gbdtransformation/brands/aptm/__init__.py
gbdtransformation/brands/aptm/filters.py
gbdtransformation/brands/aptm/schema
gbdtransformation/brands/aptm/template.yml
gbdtransformation/brands/aptm/tests/__init__.py
gbdtransformation/brands/attm/__init__.py
gbdtransformation/brands/attm/filters.py
gbdtransformation/brands/attm/schema
gbdtransformation/brands/attm/template.yml
gbdtransformation/brands/autm/__init__.py
gbdtransformation/brands/autm/filters.py
gbdtransformation/brands/autm/schema
gbdtransformation/brands/autm/template.yml
gbdtransformation/brands/bgtm/__init__.py
gbdtransformation/brands/bgtm/filters.py
gbdtransformation/brands/bgtm/schema
gbdtransformation/brands/bgtm/template.yml
gbdtransformation/brands/bhtm/__init__.py
gbdtransformation/brands/bhtm/filters.py
gbdtransformation/brands/bhtm/schema
gbdtransformation/brands/bhtm/template.yml
gbdtransformation/brands/bhtm/tests/__init__.py
gbdtransformation/brands/bntm/__init__.py
gbdtransformation/brands/bntm/filters.py
gbdtransformation/brands/bntm/schema
gbdtransformation/brands/bntm/template.yml
gbdtransformation/brands/bntm/tests/__init__.py
gbdtransformation/brands/brtm/__init__.py
gbdtransformation/brands/brtm/filters.py
gbdtransformation/brands/brtm/schema
wipo_gbd_transformation-1.1.103.dist-info/LICENSE.md
wipo_gbd_transformation-1.1.103.dist-info/METADATA
wipo_gbd_transformation-1.1.103.dist-info/WHEEL
wipo_gbd_transformation-1.1.103.dist-info/entry_points.txt
wipo_gbd_transformation-1.1.103.dist-info/top_level.txt
wipo_gbd_transformation-1.1.103.dist-info/RECORD
