Metadata-Version: 2.1
Name: wipo-gbd-transformation
Version: 1.1.103
Summary: GBD XML ETL package
Home-page: https://github.com/GBD-Wipo/xmlE
Author: WIPO GDB team
Author-email: gbd@wipo.int
License: UNKNOWN
Keywords: gbdtransformation
Platform: UNKNOWN
Classifier: Programming Language :: Python :: 3.9
License-File: LICENSE.md
Requires-Dist: PyYAML (>=5.3.1)
Requires-Dist: boto3 (>=1.16.1)
Requires-Dist: dicttoxml (>=1.7.4)
Requires-Dist: jinja2 (==2.11.2)
Requires-Dist: lingua-language-detector
Requires-Dist: lxml (>=4.6.1)
Requires-Dist: markupsafe (==2.0.1)
Requires-Dist: munch (>=2.5.0)
Requires-Dist: tabulate (>=0.8.7)
Requires-Dist: xmltodict (>=0.12.0)
